MANIFEST.in
README.md
setup.py
pvlv_interactions/__init__.py
pvlv_interactions/pvlv_interactions.py
pvlv_interactions.egg-info/PKG-INFO
pvlv_interactions.egg-info/SOURCES.txt
pvlv_interactions.egg-info/dependency_links.txt
pvlv_interactions.egg-info/top_level.txt
pvlv_interactions/configurations/__init__.py
pvlv_interactions/configurations/configuration.py
pvlv_interactions/generators/__init__.py
pvlv_interactions/generators/bad_words_generator/__init__.py
pvlv_interactions/generators/bad_words_generator/bad_words_generator.py
pvlv_interactions/generators/bad_words_generator/data/base.txt
pvlv_interactions/generators/badass_sentences/__init__.py
pvlv_interactions/generators/badass_sentences/badass_sentences.py
pvlv_interactions/generators/badass_sentences/data/eng_badass_sentences.txt
pvlv_interactions/generators/badass_sentences/data/ita_badass_sentences.txt
pvlv_interactions/generators/pickup_line/__init__.py
pvlv_interactions/generators/pickup_line/pickup_line.py
pvlv_interactions/generators/pickup_line/eng/__init__.py
pvlv_interactions/generators/pickup_line/ita/__init__.py
pvlv_interactions/static_reply/__init__.py
pvlv_interactions/static_reply/static_reply.py
pvlv_interactions/static_reply/modules/__init__.py
pvlv_interactions/static_reply/modules/reply_object.py